fdpAPIconnector/__init__.py
fdpAPIconnector/__version__.py
fdpAPIconnector/default_templates.py
fdpAPIconnector/fdpclient.py
fdpAPIconnector-0.0.5.dist-info/LICENSE
fdpAPIconnector-0.0.5.dist-info/METADATA
fdpAPIconnector-0.0.5.dist-info/WHEEL
fdpAPIconnector-0.0.5.dist-info/top_level.txt
fdpAPIconnector-0.0.5.dist-info/RECORD
