Metadata-Version: 2.1
Name: fdpAPIconnector
Version: 0.0.5
Summary: Python package to connect to a FDP API
Home-page: https://github.com/bibbox/fdpAPIconnector.py
Author: Emilian Jungwirth
Author-email: emilian.jungwirth@medunigraz.at
Project-URL: Bug Tracker, https://github.com/bibbox/fdpAPIconnector.py/issues
Classifier: Programming Language :: Python :: 3
Classifier: License :: OSI Approved :: BSD License
Classifier: Operating System :: OS Independent
Requires-Python: >=3.6
License-File: LICENSE
Requires-Dist: rdflib
Requires-Dist: requests
